prayertime.py
setup.py
prayertime.egg-info/PKG-INFO
prayertime.egg-info/SOURCES.txt
prayertime.egg-info/dependency_links.txt
prayertime.egg-info/top_level.txt