Metadata-Version: 1.1
Name: prayertime
Version: 2.4
Summary: prayertimes calculations for Python
Home-page: http://github.com/xmonader/prayertime
Author: Ahmed T. Youssef
Author-email: xmonader@gmail.com
License: BSD 3-Clause License
Platform: UNKNOWN
Classifier: Development Status :: 4 - Beta
Classifier: Environment :: Console
Classifier: Environment :: Web Environment
Classifier: Intended Audience :: Developers
Classifier: License :: OSI Approved :: BSD License
Classifier: Operating System :: OS Independent
Classifier: Programming Language :: Python
Classifier: Topic :: Software Development :: Libraries :: Python Modules
